genmotion/__init__.py
genmotion/algorithm/__init__.py
genmotion/algorithm/action2motion/__init__.py
genmotion/algorithm/action2motion/dataset.py
genmotion/algorithm/action2motion/configs/__init__.py
genmotion/algorithm/action2motion/configs/params.py
genmotion/algorithm/action2motion/lie/__init__.py
genmotion/algorithm/action2motion/lie/lie_util.py
genmotion/algorithm/action2motion/lie/pose_lie.py
genmotion/algorithm/action2motion/models/__init__.py
genmotion/algorithm/action2motion/models/motion_gan.py
genmotion/algorithm/action2motion/models/motion_vae.py
genmotion/algorithm/action2motion/trainer/__init__.py
genmotion/algorithm/action2motion/trainer/vae_trainer.py
genmotion/algorithm/action2motion/utils/__init__.py
genmotion/algorithm/action2motion/utils/matrix_transformer.py
genmotion/algorithm/action2motion/utils/paramUtil.py
genmotion/algorithm/action2motion/utils/plot_script.py
genmotion/algorithm/action2motion/utils/utils_.py
genmotion/algorithm/action_conditioned/__init__.py
genmotion/algorithm/action_conditioned/data_utils.py
genmotion/algorithm/action_conditioned/params.py
genmotion/algorithm/action_conditioned/trainer.py
genmotion/algorithm/action_conditioned/datasets/__init__.py
genmotion/algorithm/action_conditioned/datasets/dataset.py
genmotion/algorithm/action_conditioned/datasets/get_dataset.py
genmotion/algorithm/action_conditioned/datasets/humanact12poses.py
genmotion/algorithm/action_conditioned/datasets/ntu13.py
genmotion/algorithm/action_conditioned/datasets/tools.py
genmotion/algorithm/action_conditioned/datasets/uestc.py
genmotion/algorithm/action_conditioned/models/__init__.py
genmotion/algorithm/action_conditioned/models/get_model.py
genmotion/algorithm/action_conditioned/models/rotation2xyz.py
genmotion/algorithm/action_conditioned/models/smpl.py
genmotion/algorithm/action_conditioned/models/architectures/__init__.py
genmotion/algorithm/action_conditioned/models/architectures/autotrans.py
GenMotion-0.0.4.dist-info/LICENCE
GenMotion-0.0.4.dist-info/METADATA
GenMotion-0.0.4.dist-info/WHEEL
GenMotion-0.0.4.dist-info/top_level.txt
GenMotion-0.0.4.dist-info/RECORD
