Metadata-Version: 2.1
Name: GenMotion
Version: 0.0.4
Summary: Deep motion generator collections
Home-page: https://github.com/yizhouzhao/GenMotion
Author: Yizhou Zhao, Wensi Ai
Author-email: yizhouzhao@ucla.edu, va0817@ucla.edu
License: UNKNOWN
Project-URL: Bug Tracker, https://github.com/yizhouzhao/GenMotion/issues
Project-URL: Documentation, https://genmotion.readthedocs.io/en/latest
Platform: UNKNOWN
Classifier: Programming Language :: Python :: 3
Classifier: License :: OSI Approved :: MIT License
Classifier: Operating System :: OS Independent
Requires-Python: >=3.6
License-File: LICENCE
